anzu/__init__.py
anzu_workers-0.1.2.dist-info/licenses/LICENSE
anzu_workers-0.1.2.dist-info/METADATA
anzu_workers-0.1.2.dist-info/WHEEL
anzu_workers-0.1.2.dist-info/top_level.txt
anzu_workers-0.1.2.dist-info/RECORD
