Metadata-Version: 2.4
Name: anzu_workers
Version: 0.1.2
Summary: A package for updating queue items in a Django service
Home-page: https://github.com/yourusername/queue_updater
Author: Your Name
Author-email: Your Name <your.email@example.com>
License: MIT
Project-URL: Homepage, https://github.com/yourusername/queue_updater
Project-URL: Bug Tracker, https://github.com/yourusername/queue_updater/issues
Keywords: django,queue,update
Classifier: Programming Language :: Python :: 3
Classifier: License :: OSI Approved :: MIT License
Classifier: Operating System :: OS Independent
Requires-Python: >=3.6
License-File: LICENSE
Requires-Dist: requests>=2.25.0
Requires-Dist: aiohttp>=3.7.3
Requires-Dist: python-socketio>=5.12.1
Provides-Extra: langfuse
Requires-Dist: langfuse>=2.0.0; extra == "langfuse"
Provides-Extra: dev
Requires-Dist: pytest>=6.0.0; extra == "dev"
Requires-Dist: black>=22.0.0; extra == "dev"
Requires-Dist: isort>=5.0.0; extra == "dev"
Requires-Dist: mypy>=0.900; extra == "dev"
Requires-Dist: flake8>=4.0.0; extra == "dev"
Dynamic: author
Dynamic: home-page
Dynamic: license-file
Dynamic: requires-python
